hypernova_jinja2_directive/__init__.py
hypernova_jinja2_directive-0.1.0.dist-info/METADATA
hypernova_jinja2_directive-0.1.0.dist-info/WHEEL
hypernova_jinja2_directive-0.1.0.dist-info/top_level.txt
hypernova_jinja2_directive-0.1.0.dist-info/RECORD
